{
  "languageto": "Fr",
  "Change_Language_To": "Change Language To: ",
  "Free": "Free",
  "SwitchON": "SwitchON",
  "Charging": "Charging",
  "Disabled": "Disabled",
  "StopDN": "StopDown",
  "Offline": "Offline",
  "noID": "noID",
  "Ready": "Ready",
  "topup": " Top Up ",
  "logout": " Log Out ",
  "ChargeTIME": "Duration:",
  "hors": "hors",
  "bkchargehours": "plz select charge hour(s).",
  "btn_prepay": "Paystack Top Up",
  "chargerID": "chargerID:",
  "tabpaystack": "Pay stack",
  "tabvcard": "Voucher Card",
  "tabmomo": "MTN MoMo",
  "lbmomopay": "MoMo TopUp",
  "tabpaypal": "byPayPal",
  "paypalmount": "TopUP amount",
  "vcardactivenow": "vCard Active NOW",
  "vcardactiveer1": "Input Number plz",
  "vcardactiveer2": "4 digits number needed",
  "vcardactiveer3": "8 digits number needed",
  "vcardactiveer4": "Input user account plz",
  "vcardactiveer5": "invalid email address",
  "activetarget": "active user account",
  "activecode": "Active Code Number: ",
  "payfullname": "PayStack Account Full name: ",
  "mobilenumber": "MobilNumber",
  "paystackaccount": "Paystack ID: ",
  "paymoneys": "Topup moneys: ",
  "ChargeNOW": "ChargeNOW",
  "DoCharge": "DoCharge",
  "StopNOW": "StopNOW",
  "IamCharging": "IamCharging",
  "PortDisabled": "Socket Disabled",
  "StopKeyDown": "StopKey Down",
  "Clearme": "Clearme",
  "DeviceOffline": "Device Offline",
  "InvalidChargerID": "Invalid ChargerID",
  "Starting": "Starting",
  "Stoping": "Stoping"
}
